env_key_manager/__init__.py
env_key_manager/cli.py
env_key_manager/manager.py
env_key_manager-0.1.0.dist-info/licenses/LICENSE
env_key_manager-0.1.0.dist-info/METADATA
env_key_manager-0.1.0.dist-info/WHEEL
env_key_manager-0.1.0.dist-info/entry_points.txt
env_key_manager-0.1.0.dist-info/top_level.txt
env_key_manager-0.1.0.dist-info/RECORD
